{
    "users": [
        {
            "id": 95455655,
            "username": "aaiiu",
            "password": "123456",
            "name": "陶昊天",
            "department": "管理部",
            "phone": "13083437377"
        },
        {
            "id": 47083953,
            "username": "iirp",
            "password": "123456",
            "name": "周鑫鹏",
            "department": "人事部",
            "phone": "13258974312"
        },
        {
            "id": 3777051,
            "username": "elsk",
            "password": "123456",
            "name": "石风华",
            "department": "管理部",
            "phone": "13107722595"
        },
        {
            "id": 52651203,
            "username": "bpofey",
            "password": "123456",
            "name": "蒋风华",
            "department": "后勤部",
            "phone": "13419874143"
        },
        {
            "id": 86212210,
            "username": "fbgz",
            "password": "123456",
            "name": "余涛",
            "department": "人事部",
            "phone": "13092389258"
        },
        {
            "id": 71363316,
            "username": "aktwmi",
            "password": "123456",
            "name": "龙文",
            "department": "开发部",
            "phone": "13463132089"
        },
        {
            "id": 72967229,
            "username": "wzpgur",
            "password": "123456",
            "name": "任熠彤",
            "department": "开发部",
            "phone": "13617819526"
        },
        {
            "id": 61486224,
            "username": "joigil",
            "password": "123456",
            "name": "朱峻熙",
            "department": "管理部",
            "phone": "13546884415"
        },
        {
            "id": 860284,
            "username": "xgva",
            "password": "123456",
            "name": "贾睿渊",
            "department": "人事部",
            "phone": "13255847059"
        },
        {
            "id": 8170073,
            "username": "iuif",
            "password": "123456",
            "name": "张懿轩",
            "department": "管理部",
            "phone": "13103390176"
        },
        {
            "id": 57656374,
            "username": "yktew",
            "password": "123456",
            "name": "魏子轩",
            "department": "开发部",
            "phone": "13244265685"
        },
        {
            "id": 5925309,
            "username": "znjon",
            "password": "123456",
            "name": "张晋鹏",
            "department": "开发部",
            "phone": "13537411351"
        },
        {
            "id": 97852796,
            "username": "gswjpz",
            "password": "123456",
            "name": "姜越泽",
            "department": "人事部",
            "phone": "13959180381"
        },
        {
            "id": 36502176,
            "username": "nerzw",
            "password": "123456",
            "name": "邓琪",
            "department": "人事部",
            "phone": "13383835034"
        },
        {
            "id": 2259686,
            "username": "curtv",
            "password": "123456",
            "name": "陈鹭洋",
            "department": "开发部",
            "phone": "13674370817"
        },
        {
            "id": 48879784,
            "username": "dvejne",
            "password": "123456",
            "name": "阎越彬",
            "department": "管理部",
            "phone": "13790181084"
        },
        {
            "id": 94901593,
            "username": "tpxzh",
            "password": "123456",
            "name": "毛烨霖",
            "department": "人事部",
            "phone": "13237781062"
        },
        {
            "id": 19383689,
            "username": "vtohdv",
            "password": "123456",
            "name": "侯智渊",
            "department": "管理部",
            "phone": "13179303896"
        },
        {
            "id": 88670497,
            "username": "fztes",
            "password": "123456",
            "name": "尹明杰",
            "department": "人事部",
            "phone": "13831614464"
        },
        {
            "id": 37716011,
            "username": "sllc",
            "password": "123456",
            "name": "傅志泽",
            "department": "管理部",
            "phone": "13289611513"
        },
        {
            "id": 43909705,
            "username": "kalooy",
            "password": "123456",
            "name": "冯耀杰",
            "department": "人事部",
            "phone": "13733835040"
        },
        {
            "id": 66236231,
            "username": "tnib",
            "password": "123456",
            "name": "秦鹤轩",
            "department": "人事部",
            "phone": "13675356649"
        },
        {
            "id": 57034294,
            "username": "jhzr",
            "password": "123456",
            "name": "程彬",
            "department": "管理部",
            "phone": "13805861525"
        },
        {
            "id": 28577279,
            "username": "glvrd",
            "password": "123456",
            "name": "姜健柏",
            "department": "开发部",
            "phone": "13708823764"
        },
        {
            "id": 5134657,
            "username": "dilliw",
            "password": "123456",
            "name": "陆聪健",
            "department": "管理部",
            "phone": "13169060571"
        },
        {
            "id": 44375646,
            "username": "jryp",
            "password": "123456",
            "name": "宋鹭洋",
            "department": "开发部",
            "phone": "13550877747"
        },
        {
            "id": 82022665,
            "username": "mxmdrv",
            "password": "123456",
            "name": "薛炫明",
            "department": "后勤部",
            "phone": "13088056933"
        },
        {
            "id": 96896914,
            "username": "jwrqr",
            "password": "123456",
            "name": "洪鑫磊",
            "department": "后勤部",
            "phone": "13638086031"
        },
        {
            "id": 67656940,
            "username": "iters",
            "password": "123456",
            "name": "尹昊焱",
            "department": "开发部",
            "phone": "13361733465"
        },
        {
            "id": 5442668,
            "username": "lnde",
            "password": "123456",
            "name": "袁越泽",
            "department": "后勤部",
            "phone": "13013385900"
        },
        {
            "id": 23106612,
            "username": "yuir",
            "password": "123456",
            "name": "孟煜祺",
            "department": "开发部",
            "phone": "13347302425"
        },
        {
            "id": 4546453,
            "username": "hsxohh",
            "password": "123456",
            "name": "贺健柏",
            "department": "管理部",
            "phone": "13037515008"
        },
        {
            "id": 84723783,
            "username": "ehsio",
            "password": "123456",
            "name": "任瑾瑜",
            "department": "开发部",
            "phone": "13220522335"
        },
        {
            "id": 2420973,
            "username": "fhlvi",
            "password": "123456",
            "name": "夏思远",
            "department": "后勤部",
            "phone": "13625961473"
        },
        {
            "id": 21538611,
            "username": "ghrly",
            "password": "123456",
            "name": "覃耀杰",
            "department": "开发部",
            "phone": "13053870950"
        },
        {
            "id": 97821130,
            "username": "ymsl",
            "password": "123456",
            "name": "孔文昊",
            "department": "后勤部",
            "phone": "13438733888"
        },
        {
            "id": 94190002,
            "username": "jcajm",
            "password": "123456",
            "name": "汪俊驰",
            "department": "后勤部",
            "phone": "13274322437"
        },
        {
            "id": 18227742,
            "username": "rpiuv",
            "password": "123456",
            "name": "曾熠彤",
            "department": "管理部",
            "phone": "13641700967"
        },
        {
            "id": 76154994,
            "username": "sbawzu",
            "password": "123456",
            "name": "胡浩",
            "department": "开发部",
            "phone": "13700780251"
        },
        {
            "id": 75208022,
            "username": "pimo",
            "password": "123456",
            "name": "顾鹏飞",
            "department": "开发部",
            "phone": "13963228007"
        },
        {
            "id": 83447128,
            "username": "djjks",
            "password": "123456",
            "name": "邓思",
            "department": "后勤部",
            "phone": "13672493010"
        },
        {
            "id": 51489294,
            "username": "tpngtx",
            "password": "123456",
            "name": "吕烨霖",
            "department": "管理部",
            "phone": "13976790704"
        },
        {
            "id": 427977,
            "username": "dast",
            "password": "123456",
            "name": "龙鹏",
            "department": "人事部",
            "phone": "13232958150"
        },
        {
            "id": 48839146,
            "username": "gbiiox",
            "password": "123456",
            "name": "杨乐驹",
            "department": "后勤部",
            "phone": "13975839171"
        },
        {
            "id": 51300863,
            "username": "nydry",
            "password": "123456",
            "name": "王乐驹",
            "department": "后勤部",
            "phone": "13697058909"
        },
        {
            "id": 48299081,
            "username": "odifw",
            "password": "123456",
            "name": "孟立果",
            "department": "开发部",
            "phone": "13010135016"
        },
        {
            "id": 42042536,
            "username": "ourh",
            "password": "123456",
            "name": "傅明辉",
            "department": "开发部",
            "phone": "13422859566"
        },
        {
            "id": 86924433,
            "username": "zzxyi",
            "password": "123456",
            "name": "谭晓博",
            "department": "后勤部",
            "phone": "13608386320"
        },
        {
            "id": 55015170,
            "username": "iezm",
            "password": "123456",
            "name": "白靖琪",
            "department": "开发部",
            "phone": "13106594795"
        },
        {
            "id": 9520482,
            "username": "jldgjy",
            "password": "123456",
            "name": "杨天磊",
            "department": "管理部",
            "phone": "13251323715"
        },
        {
            "id": 16290617,
            "username": "pxhl",
            "password": "123456",
            "name": "冯志泽",
            "department": "人事部",
            "phone": "13590853659"
        },
        {
            "id": 76621792,
            "username": "vmshcl",
            "password": "123456",
            "name": "孟立轩",
            "department": "人事部",
            "phone": "13656876919"
        },
        {
            "id": 16384739,
            "username": "dsez",
            "password": "123456",
            "name": "董鸿煊",
            "department": "后勤部",
            "phone": "13850633327"
        },
        {
            "id": 69505331,
            "username": "nbbbhp",
            "password": "123456",
            "name": "陆昊强",
            "department": "后勤部",
            "phone": "13431662321"
        },
        {
            "id": 39210995,
            "username": "kptanz",
            "password": "123456",
            "name": "武立诚",
            "department": "后勤部",
            "phone": "13968471096"
        },
        {
            "id": 48571210,
            "username": "pbrx",
            "password": "123456",
            "name": "许鹏",
            "department": "开发部",
            "phone": "13265460311"
        },
        {
            "id": 11624981,
            "username": "wxxj",
            "password": "123456",
            "name": "邵昊焱",
            "department": "后勤部",
            "phone": "13811971112"
        },
        {
            "id": 23610865,
            "username": "mujf",
            "password": "123456",
            "name": "林瑾瑜",
            "department": "开发部",
            "phone": "13690722446"
        },
        {
            "id": 85479627,
            "username": "wghveb",
            "password": "123456",
            "name": "雷睿渊",
            "department": "管理部",
            "phone": "13525143901"
        },
        {
            "id": 41281418,
            "username": "attz",
            "password": "123456",
            "name": "段明辉",
            "department": "开发部",
            "phone": "13943645032"
        },
        {
            "id": 93149489,
            "username": "awqesv",
            "password": "123456",
            "name": "秦浩然",
            "department": "管理部",
            "phone": "13021034885"
        },
        {
            "id": 21955439,
            "username": "wruuv",
            "password": "123456",
            "name": "姚明杰",
            "department": "开发部",
            "phone": "13716757803"
        },
        {
            "id": 15128430,
            "username": "kwejt",
            "password": "123456",
            "name": "阎绍辉",
            "department": "开发部",
            "phone": "13336115409"
        },
        {
            "id": 75531127,
            "username": "gkszw",
            "password": "123456",
            "name": "林哲瀚",
            "department": "管理部",
            "phone": "13851401940"
        },
        {
            "id": 14182142,
            "username": "bguj",
            "password": "123456",
            "name": "萧昊强",
            "department": "开发部",
            "phone": "13662115506"
        },
        {
            "id": 73707974,
            "username": "yvnafy",
            "password": "123456",
            "name": "刘博文",
            "department": "管理部",
            "phone": "13686895086"
        },
        {
            "id": 84757298,
            "username": "zygchj",
            "password": "123456",
            "name": "孔思远",
            "department": "开发部",
            "phone": "13677859663"
        },
        {
            "id": 59635992,
            "username": "gyjdw",
            "password": "123456",
            "name": "赖弘文",
            "department": "后勤部",
            "phone": "13951752166"
        },
        {
            "id": 40228557,
            "username": "oddvf",
            "password": "123456",
            "name": "严晋鹏",
            "department": "后勤部",
            "phone": "13918899681"
        },
        {
            "id": 9404394,
            "username": "jkozi",
            "password": "123456",
            "name": "李文昊",
            "department": "管理部",
            "phone": "13274162768"
        },
        {
            "id": 89671710,
            "username": "xlqfkk",
            "password": "123456",
            "name": "洪昊然",
            "department": "后勤部",
            "phone": "13485981094"
        },
        {
            "id": 21721364,
            "username": "uzyh",
            "password": "123456",
            "name": "戴博文",
            "department": "管理部",
            "phone": "13614914325"
        },
        {
            "id": 2091896,
            "username": "bpdqkr",
            "password": "123456",
            "name": "胡炎彬",
            "department": "人事部",
            "phone": "13651851103"
        },
        {
            "id": 8129691,
            "username": "gsofkf",
            "password": "123456",
            "name": "高晟睿",
            "department": "开发部",
            "phone": "13670609475"
        },
        {
            "id": 71505954,
            "username": "onrvj",
            "password": "123456",
            "name": "侯天翊",
            "department": "后勤部",
            "phone": "13959520607"
        },
        {
            "id": 33326897,
            "username": "wumy",
            "password": "123456",
            "name": "贺潇然",
            "department": "管理部",
            "phone": "13425184098"
        },
        {
            "id": 4699152,
            "username": "duuy",
            "password": "123456",
            "name": "杜聪健",
            "department": "人事部",
            "phone": "13555001411"
        },
        {
            "id": 86740030,
            "username": "dpsb",
            "password": "123456",
            "name": "戴煜城",
            "department": "人事部",
            "phone": "13802116218"
        },
        {
            "id": 5911679,
            "username": "ewfdxy",
            "password": "123456",
            "name": "沈涛",
            "department": "管理部",
            "phone": "13602478453"
        },
        {
            "id": 44392361,
            "username": "zxanvl",
            "password": "123456",
            "name": "韩鸿涛",
            "department": "后勤部",
            "phone": "13177412346"
        },
        {
            "id": 10560918,
            "username": "tlze",
            "password": "123456",
            "name": "蒋立轩",
            "department": "人事部",
            "phone": "13278941653"
        },
        {
            "id": 3018241,
            "username": "cmtrg",
            "password": "123456",
            "name": "唐鹏飞",
            "department": "后勤部",
            "phone": "13174350203"
        },
        {
            "id": 55111463,
            "username": "lcqnw",
            "password": "123456",
            "name": "孟风华",
            "department": "后勤部",
            "phone": "13708561285"
        },
        {
            "id": 99373059,
            "username": "kpcg",
            "password": "123456",
            "name": "曹涛",
            "department": "人事部",
            "phone": "13182171415"
        },
        {
            "id": 87162980,
            "username": "axtnet",
            "password": "123456",
            "name": "沈修杰",
            "department": "后勤部",
            "phone": "13555332178"
        },
        {
            "id": 78551771,
            "username": "elbjaq",
            "password": "123456",
            "name": "方文轩",
            "department": "开发部",
            "phone": "13858629985"
        },
        {
            "id": 41533904,
            "username": "pxitl",
            "password": "123456",
            "name": "孙楷瑞",
            "department": "开发部",
            "phone": "13510456896"
        },
        {
            "id": 51193873,
            "username": "rijdm",
            "password": "123456",
            "name": "方子轩",
            "department": "管理部",
            "phone": "13391930821"
        },
        {
            "id": 7188577,
            "username": "mzkx",
            "password": "123456",
            "name": "林炎彬",
            "department": "开发部",
            "phone": "13949028609"
        },
        {
            "id": 4679867,
            "username": "sfmoo",
            "password": "123456",
            "name": "曾越泽",
            "department": "人事部",
            "phone": "13985300383"
        },
        {
            "id": 97882357,
            "username": "cqqo",
            "password": "123456",
            "name": "胡炎彬",
            "department": "人事部",
            "phone": "13771230025"
        },
        {
            "id": 75060409,
            "username": "egxa",
            "password": "123456",
            "name": "方烨华",
            "department": "后勤部",
            "phone": "13233526123"
        },
        {
            "id": 63029852,
            "username": "whaa",
            "password": "123456",
            "name": "胡彬",
            "department": "人事部",
            "phone": "13728797943"
        },
        {
            "id": 50715545,
            "username": "tmuzbw",
            "password": "123456",
            "name": "卢乐驹",
            "department": "开发部",
            "phone": "13011631930"
        },
        {
            "id": 7696026,
            "username": "ojyvw",
            "password": "123456",
            "name": "钟伟泽",
            "department": "开发部",
            "phone": "13837903790"
        },
        {
            "id": 93466891,
            "username": "qjlu",
            "password": "123456",
            "name": "贾明轩",
            "department": "人事部",
            "phone": "13042879059"
        },
        {
            "id": 66078192,
            "username": "vvtryq",
            "password": "123456",
            "name": "傅修杰",
            "department": "开发部",
            "phone": "13276277914"
        },
        {
            "id": 59063046,
            "username": "wiiq",
            "password": "123456",
            "name": "汪致远",
            "department": "管理部",
            "phone": "13422404560"
        },
        {
            "id": 61322489,
            "username": "wkawm",
            "password": "123456",
            "name": "谢智渊",
            "department": "管理部",
            "phone": "13310122728"
        },
        {
            "id": 17547005,
            "username": "tkfew",
            "password": "123456",
            "name": "雷博涛",
            "department": "开发部",
            "phone": "13462586520"
        }
    ]
}
